Matplotlib30MijiChuyiFix1/README.md
Matplotlib30MijiChuyiFix1/__init__.py
Matplotlib30MijiChuyiFix1/__main__.py
Matplotlib30MijiChuyiFix1/file.epub
Matplotlib30MijiChuyiFix1/index.html
Matplotlib30MijiChuyiFix1/css/__init__.py
Matplotlib30MijiChuyiFix1/css/annotations.css
Matplotlib30MijiChuyiFix1/css/main.css
Matplotlib30MijiChuyiFix1/css/normalize.css
Matplotlib30MijiChuyiFix1/css/popup.css
Matplotlib30MijiChuyiFix1/font/__init__.py
Matplotlib30MijiChuyiFix1/font/fontello.eot
Matplotlib30MijiChuyiFix1/font/fontello.svg
Matplotlib30MijiChuyiFix1/font/fontello.ttf
Matplotlib30MijiChuyiFix1/font/fontello.woff
Matplotlib30MijiChuyiFix1/img/__init__.py
Matplotlib30MijiChuyiFix1/img/annotator-glyph-sprite.png
Matplotlib30MijiChuyiFix1/img/annotator-icon-sprite.png
Matplotlib30MijiChuyiFix1/img/apple-touch-icon.png
Matplotlib30MijiChuyiFix1/img/cancelfullscreen.png
Matplotlib30MijiChuyiFix1/img/close.png
Matplotlib30MijiChuyiFix1/img/fullscreen.png
Matplotlib30MijiChuyiFix1/img/loader.gif
Matplotlib30MijiChuyiFix1/img/menu-icon.png
Matplotlib30MijiChuyiFix1/img/save.png
Matplotlib30MijiChuyiFix1/img/saved.png
Matplotlib30MijiChuyiFix1/img/settings-s.png
Matplotlib30MijiChuyiFix1/img/settings.png
Matplotlib30MijiChuyiFix1/img/star.png
Matplotlib30MijiChuyiFix1/js/__init__.py
Matplotlib30MijiChuyiFix1/js/epub.js
Matplotlib30MijiChuyiFix1/js/epub.min.js
Matplotlib30MijiChuyiFix1/js/epub.min.map
Matplotlib30MijiChuyiFix1/js/hooks.min.js
Matplotlib30MijiChuyiFix1/js/hooks.min.map
Matplotlib30MijiChuyiFix1/js/reader.js
Matplotlib30MijiChuyiFix1/js/reader.js.map
Matplotlib30MijiChuyiFix1/js/reader.min.js
Matplotlib30MijiChuyiFix1/js/reader.min.map
Matplotlib30MijiChuyiFix1/js/hooks/__init__.py
Matplotlib30MijiChuyiFix1/js/hooks/extensions/__init__.py
Matplotlib30MijiChuyiFix1/js/hooks/extensions/highlight.js
Matplotlib30MijiChuyiFix1/js/libs/__init__.py
Matplotlib30MijiChuyiFix1/js/libs/jquery.min.js
Matplotlib30MijiChuyiFix1/js/libs/localforage.min.js
matplotlib_3_0_miji_chuyi_fix1-2025.3.24.0.dist-info/METADATA
matplotlib_3_0_miji_chuyi_fix1-2025.3.24.0.dist-info/WHEEL
matplotlib_3_0_miji_chuyi_fix1-2025.3.24.0.dist-info/entry_points.txt
matplotlib_3_0_miji_chuyi_fix1-2025.3.24.0.dist-info/top_level.txt
matplotlib_3_0_miji_chuyi_fix1-2025.3.24.0.dist-info/RECORD
